pandas_mcp_server/__init__.py
pandas_mcp_server/cli.py
pandas_mcp_server/server.py
pandas_mcp_server/core/__init__.py
pandas_mcp_server/core/config.py
pandas_mcp_server/core/data_types.py
pandas_mcp_server/core/execution.py
pandas_mcp_server/core/metadata.py
pandas_mcp_server/core/visualization.py
pandas_mcp_server/core/chart_generators/__init__.py
pandas_mcp_server/core/chart_generators/bar.py
pandas_mcp_server/core/chart_generators/base.py
pandas_mcp_server/core/chart_generators/line.py
pandas_mcp_server/core/chart_generators/pie.py
pandas_mcp-0.1.8.dist-info/METADATA
pandas_mcp-0.1.8.dist-info/WHEEL
pandas_mcp-0.1.8.dist-info/entry_points.txt
pandas_mcp-0.1.8.dist-info/top_level.txt
pandas_mcp-0.1.8.dist-info/RECORD
