Metadata-Version: 2.4
Name: pandas-mcp
Version: 0.1.8
Summary: An unofficial, packaged release of Marlon Luo's pandas-mcp-server for easy installation.
Author-email: Marlon Luo <marlonluo2018@gmail.com>
Maintainer-email: Peter Kuik <peter_kuik@epam.com>
License-Expression: MIT
Classifier: Programming Language :: Python :: 3
Classifier: Operating System :: OS Independent
Requires-Python: >=3.8
Requires-Dist: pandas>=2.0.0
Requires-Dist: chardet>=5.0.0
Requires-Dist: fastmcp>=1.0.0
Requires-Dist: psutil>=5.9.0
